uace/__init__.py
uace/cli.py
uace/config.py
uace/engine.py
uace/models.py
uace/chunking/__init__.py
uace/chunking/semantic.py
uace/cleaning/__init__.py
uace/cleaning/engine.py
uace/diarization/__init__.py
uace/engines/__init__.py
uace/engines/transcription.py
uace/export/__init__.py
uace/export/formats.py
uace/styling/__init__.py
uace/styling/presets.py
uace/utils/__init__.py
uace/utils/burnin.py
uace/utils/helpers.py
uace/utils/logging.py
uace-0.1.4.dist-info/licenses/LICENSE
uace-0.1.4.dist-info/METADATA
uace-0.1.4.dist-info/WHEEL
uace-0.1.4.dist-info/entry_points.txt
uace-0.1.4.dist-info/top_level.txt
uace-0.1.4.dist-info/RECORD
