Metadata-Version: 2.4
Name: uace
Version: 0.1.4
Summary: Universal Auto-Caption Engine - Speech refinement with motion typography
Author-email: Chigozie Anyaeji <chigozieanyaeji@gmail.com>
License: MIT
Project-URL: Homepage, https://github.com/chigozie-coder/uace
Project-URL: Documentation, https://github.com/chigozie-coder/uace
Project-URL: Repository, https://github.com/chigozie-coder/uace
Project-URL: Issues, https://github.com/chigozie-coder/uace/issues
Keywords: captions,subtitles,whisper,transcription,video,accessibility,motion-typography
Classifier: Development Status :: 4 - Beta
Classifier: Intended Audience :: Developers
Classifier: Intended Audience :: End Users/Desktop
Classifier: License :: OSI Approved :: MIT License
Classifier: Operating System :: OS Independent
Classifier: Programming Language :: Python :: 3
Classifier: Programming Language :: Python :: 3.9
Classifier: Programming Language :: Python :: 3.10
Classifier: Programming Language :: Python :: 3.11
Classifier: Programming Language :: Python :: 3.12
Classifier: Topic :: Multimedia :: Video
Classifier: Topic :: Scientific/Engineering :: Artificial Intelligence
Requires-Python: >=3.9
License-File: LICENSE
Requires-Dist: numpy>=1.24.0
Requires-Dist: pydantic>=2.0.0
Requires-Dist: rich>=13.0.0
Requires-Dist: click>=8.0.0
Provides-Extra: whisper
Requires-Dist: faster-whisper>=1.0.0; extra == "whisper"
Requires-Dist: torch>=2.0.0; extra == "whisper"
Provides-Extra: whisperx
Requires-Dist: whisperx>=3.1.0; extra == "whisperx"
Requires-Dist: torch>=2.0.0; extra == "whisperx"
Requires-Dist: torchaudio>=2.0.0; extra == "whisperx"
Provides-Extra: distil
Requires-Dist: transformers>=4.30.0; extra == "distil"
Requires-Dist: torch>=2.0.0; extra == "distil"
Provides-Extra: video
Requires-Dist: ffmpeg-python>=0.2.0; extra == "video"
Provides-Extra: all
Requires-Dist: faster-whisper>=1.0.0; extra == "all"
Requires-Dist: whisperx>=3.1.0; extra == "all"
Requires-Dist: transformers>=4.30.0; extra == "all"
Requires-Dist: torch>=2.0.0; extra == "all"
Requires-Dist: torchaudio>=2.0.0; extra == "all"
Requires-Dist: ffmpeg-python>=0.2.0; extra == "all"
Provides-Extra: dev
Requires-Dist: pytest>=7.0.0; extra == "dev"
Requires-Dist: pytest-cov>=4.0.0; extra == "dev"
Requires-Dist: black>=23.0.0; extra == "dev"
Requires-Dist: ruff>=0.1.0; extra == "dev"
Requires-Dist: mypy>=1.0.0; extra == "dev"
Requires-Dist: pre-commit>=3.0.0; extra == "dev"
Dynamic: license-file
